MANIFEST.in
README.md
setup.py
mugen/__init__.py
mugen/adapters.py
mugen/api.py
mugen/connect.py
mugen/connection_pool.py
mugen/cookies.py
mugen/exceptions.py
mugen/models.py
mugen/proxy.py
mugen/session.py
mugen/structures.py
mugen/utils.py
mugen.egg-info/PKG-INFO
mugen.egg-info/SOURCES.txt
mugen.egg-info/dependency_links.txt
mugen.egg-info/requires.txt
mugen.egg-info/top_level.txt