Metadata-Version: 1.1
Name: mugen
Version: 0.4.4
Summary: Mugen is library for http asynchronous requests
Home-page: http://github.com/PeterDing/mugen
Author: PeterDing
Author-email: dfhasyt@gmail.com
License: Apache 2.0
Platform: UNKNOWN
Classifier: License :: OSI Approved :: Apache Software License
Classifier: Programming Language :: Python
Classifier: Programming Language :: Python :: 3
Classifier: Programming Language :: Python :: 3.4
Classifier: Programming Language :: Python :: 3.5
